{
  "time": "2020-10-06 20:55:31",
  "data": [
    {
      "area": "JJL2F",
      "now": "135",
      "all": "180"
    },
    {
      "area": "JJL3F",
      "now": "126",
      "all": "280"
    },
    {
      "area": "MGG2F",
      "now": "113",
      "all": "186"
    },
    {
      "area": "JJL4F",
      "now": "114",
      "all": "260"
    },
    {
      "area": "MGG4F",
      "now": "70",
      "all": "140"
    },
    {
      "area": "TMH",
      "now": "16",
      "all": "70"
    },
    {
      "area": "JJL6F",
      "now": "38",
      "all": "150"
    },
    {
      "area": "JJL5F",
      "now": "73",
      "all": "255"
    },
    {
      "area": "MGG3F",
      "now": "103",
      "all": "205"
    }
  ]
}