{
  "time": "2020-10-06 09:34:24",
  "data": [
    {
      "area": "JJL6F",
      "now": "35",
      "all": "150"
    },
    {
      "area": "JJL2F",
      "now": "104",
      "all": "180"
    },
    {
      "area": "MGG4F",
      "now": "49",
      "all": "140"
    },
    {
      "area": "MGG3F",
      "now": "80",
      "all": "205"
    },
    {
      "area": "MGG2F",
      "now": "95",
      "all": "186"
    },
    {
      "area": "JJL3F",
      "now": "115",
      "all": "280"
    },
    {
      "area": "JJL4F",
      "now": "88",
      "all": "260"
    },
    {
      "area": "JJL5F",
      "now": "57",
      "all": "255"
    },
    {
      "area": "TMH",
      "now": "14",
      "all": "70"
    }
  ]
}