{
  "time": "2020-10-10 18:55:30",
  "data": [
    {
      "area": "JJL5F",
      "now": "186",
      "all": "255"
    },
    {
      "area": "JJL6F",
      "now": "91",
      "all": "150"
    },
    {
      "area": "MGG2F",
      "now": "150",
      "all": "186"
    },
    {
      "area": "JJL4F",
      "now": "235",
      "all": "260"
    },
    {
      "area": "JJL3F",
      "now": "279",
      "all": "280"
    },
    {
      "area": "MGG3F",
      "now": "133",
      "all": "205"
    },
    {
      "area": "MGG4F",
      "now": "76",
      "all": "140"
    },
    {
      "area": "TMH",
      "now": "68",
      "all": "70"
    },
    {
      "area": "JJL2F",
      "now": "180",
      "all": "180"
    }
  ]
}