{
  "time": "2021-03-05 04:26:25",
  "data": [
    {
      "area": "MGG2F",
      "now": "1",
      "all": "186"
    },
    {
      "area": "MGG3F",
      "now": "1",
      "all": "205"
    },
    {
      "area": "MGG4F",
      "now": "1",
      "all": "140"
    },
    {
      "area": "JJL2F",
      "now": "9",
      "all": "250"
    },
    {
      "area": "JJL3F",
      "now": "8",
      "all": "430"
    },
    {
      "area": "JJL4F",
      "now": "8",
      "all": "400"
    },
    {
      "area": "JJL5F",
      "now": "6",
      "all": "320"
    },
    {
      "area": "JJL6F",
      "now": "2",
      "all": "200"
    },
    {
      "area": "TMH",
      "now": "4",
      "all": "70"
    }
  ]
}