{
  "time": "2021-03-02 15:22:39",
  "data": [
    {
      "area": "MGG3F",
      "now": "81",
      "all": "205"
    },
    {
      "area": "JJL5F",
      "now": "189",
      "all": "255"
    },
    {
      "area": "MGG2F",
      "now": "169",
      "all": "186"
    },
    {
      "area": "JJL6F",
      "now": "119",
      "all": "150"
    },
    {
      "area": "JJL2F",
      "now": "179",
      "all": "180"
    },
    {
      "area": "MGG4F",
      "now": "58",
      "all": "140"
    },
    {
      "area": "JJL3F",
      "now": "280",
      "all": "280"
    },
    {
      "area": "TMH",
      "now": "42",
      "all": "70"
    },
    {
      "area": "JJL4F",
      "now": "233",
      "all": "260"
    }
  ]
}