{
  "time": "2021-03-14 15:59:23",
  "data": [
    {
      "area": "JJL4F",
      "now": "390",
      "all": "400"
    },
    {
      "area": "JJL2F",
      "now": "249",
      "all": "250"
    },
    {
      "area": "MGG4F",
      "now": "88",
      "all": "140"
    },
    {
      "area": "JJL5F",
      "now": "317",
      "all": "320"
    },
    {
      "area": "MGG3F",
      "now": "147",
      "all": "205"
    },
    {
      "area": "JJL6F",
      "now": "199",
      "all": "200"
    },
    {
      "area": "JJL3F",
      "now": "423",
      "all": "430"
    },
    {
      "area": "MGG2F",
      "now": "173",
      "all": "186"
    },
    {
      "area": "TMH",
      "now": "68",
      "all": "70"
    }
  ]
}